ssm_parameter_config/__init__.py
ssm_parameter_config/_yaml.py
ssm_parameter_config/py.typed
ssm_parameter_config/ssm_config.py
ssm_parameter_config/ssm_parameter.py
ssm_parameter_config/ssm_path.py
ssm_parameter_config/ssm_writer.py
ssm_parameter_config/utils.py
ssm_parameter_config-1.1.3.dist-info/entry_points.txt
ssm_parameter_config-1.1.3.dist-info/METADATA
ssm_parameter_config-1.1.3.dist-info/LICENSE
ssm_parameter_config-1.1.3.dist-info/WHEEL
ssm_parameter_config-1.1.3.dist-info/RECORD
