Metadata-Version: 2.1
Name: ssm-parameter-config
Version: 1.1.3
Summary: Description
Home-page: https://github.com/mumblepins/ssm-parameter-config/
License: MIT
Author: Daniel Sullivan
Author-email: daniel.j.sullivan@state.mn.us
Requires-Python: >=3.9,<4.0
Classifier: License :: OSI Approved :: MIT License
Classifier: Programming Language :: Python :: 3
Classifier: Programming Language :: Python :: 3.9
Classifier: Programming Language :: Python :: 3.10
Classifier: Programming Language :: Python :: 3.11
Requires-Dist: boto3
Requires-Dist: botocore
Requires-Dist: click (>=7.0)
Requires-Dist: pydantic
Requires-Dist: python-dotenv
Requires-Dist: ruamel.yaml
Requires-Dist: signed-pickle (>=1)
Project-URL: Documentation, https://mumblepins.github.io/ssm-parameter-config/
Project-URL: Repository, https://github.com/mumblepins/ssm-parameter-config/
